{
  "openapi": "3.0.1",
  "info": {
    "title": "URL Shortner",
    "description": "",
    "version": "1.0.0"
  },
  "tags": [],
  "paths": {
    "/api/login": {
      "post": {
        "summary": "Login",
        "deprecated": false,
        "description": "",
        "tags": [],
        "parameters": [],
        "responses": {
          "200": {
            "description": "",
            "content": {
              "application/json": {
                "schema": {
                  "type": "object",
                  "properties": {}
                }
              }
            },
            "headers": {}
          }
        },
        "security": []
      }
    },
    "/api/register": {
      "post": {
        "summary": "Register",
        "deprecated": false,
        "description": "",
        "tags": [],
        "parameters": [],
        "responses": {
          "200": {
            "description": "",
            "content": {
              "application/json": {
                "schema": {
                  "type": "object",
                  "properties": {}
                }
              }
            },
            "headers": {}
          }
        },
        "security": []
      }
    },
    "/api/transfer": {
      "post": {
        "summary": "Transfer",
        "deprecated": false,
        "description": "",
        "tags": [],
        "parameters": [],
        "responses": {
          "200": {
            "description": "",
            "content": {
              "application/json": {
                "schema": {
                  "type": "object",
                  "properties": {}
                }
              }
            },
            "headers": {}
          }
        },
        "security": [
          {
            "bearer": []
          }
        ]
      }
    },
    "/api/transactions": {
      "get": {
        "summary": "Transaction List",
        "deprecated": false,
        "description": "",
        "tags": [],
        "parameters": [],
        "responses": {
          "200": {
            "description": "",
            "content": {
              "application/json": {
                "schema": {
                  "type": "object",
                  "properties": {}
                }
              }
            },
            "headers": {}
          }
        },
        "security": [
          {
            "bearer": []
          }
        ]
      }
    },
    "/api/wallet": {
      "get": {
        "summary": "GetWalletBalance",
        "deprecated": false,
        "description": "",
        "tags": [],
        "parameters": [],
        "responses": {
          "200": {
            "description": "",
            "content": {
              "application/json": {
                "schema": {
                  "type": "object",
                  "properties": {}
                }
              }
            },
            "headers": {}
          }
        },
        "security": [
          {
            "bearer": []
          }
        ]
      }
    }
  },
  "components": {
    "schemas": {},
    "securitySchemes": {
      "bearer": {
        "type": "http",
        "scheme": "bearer"
      }
    }
  },
  "servers": [],
  "security": []
}